nwdata/__init__.py
nwdata/datasets/__init__.py
nwdata/datasets/dataset.py
nwdata/datasets/mnist_reader.py
nwdata/datasets/carla/__init__.py
nwdata/datasets/carla/carla_npy_reader.py
nwdata/datasets/carla/carla_png_reader.py
nwdata/datasets/carla/plot_utils.py
nwdata/datasets/nyudepthv2/__init__.py
nwdata/datasets/nyudepthv2/normalizers.py
nwdata/datasets/nyudepthv2/nyudepthv2_h5_paths_reader.py
nwdata/datasets/sfmlearner/__init__.py
nwdata/datasets/sfmlearner/sfmlearner_generic_reader.py
nwdata/datasets/sfmlearner/sfmlearner_video_npy_reader.py
nwdata/datasets/sfmlearner/sfmlearner_video_reader.py
nwdata/reader/__init__.py
nwdata/reader/batched_reader.py
nwdata/reader/epoch_iterator.py
nwdata/reader/generator.py
nwdata/reader/h5_batched_reader.py
nwdata/reader/random_index.py
nwdata/reader/reader.py
nwdata/reader/schema.py
nwdata/reader/builder/__init__.py
nwdata/reader/builder/builder_reader.py
nwdata/reader/builder/cached_reader.py
nwdata/reader/builder/combined_reader.py
nwdata/reader/builder/debug_reader.py
nwdata/reader/builder/merge_batched_reader.py
nwdata/reader/builder/percent_reader.py
nwdata/reader/builder/random_index_reader.py
nwdata/reader/builder/random_sized_batched_reader.py
nwdata/reader/builder/split_reader.py
nwdata/reader/builder/static_batched_reader.py
nwdata/utils/__init__.py
nwdata/utils/batched_utils.py
nwdata/utils/data_structures_utils.py
nwdata/utils/data_utils.py
nwdata/utils/dict_utils.py
nwdata/utils/h5_utils.py
nwdata/utils/index_utils.py
nwdata/utils/list_utils.py
nwdata/utils/np_utils.py
nwdata/utils/path_utils.py
nwdata/utils/unreal_utils.py
nwdata/utils/others/__init__.py
nwdata/utils/others/fake_args.py
nwdata/utils/others/nwgenerator.py
nwdata/utils/others/others.py
nwdata/utils/others/running_mean.py
nwdata/utils/others/topological_sort.py
nwdata-0.1.dist-info/LICENSE.TXT
nwdata-0.1.dist-info/METADATA
nwdata-0.1.dist-info/WHEEL
nwdata-0.1.dist-info/top_level.txt
nwdata-0.1.dist-info/RECORD
