Metadata-Version: 2.1
Name: nwdata
Version: 0.1
Summary: Generic Dataset Reader high level API
Home-page: https://gitlab.com/neuralwrappers/nwdata
Author: Mihai Cristian Pîrvu
Author-email: mihaicristianpirvu@gmail.com
License: WTFPL
Keywords: dataset,reader,high level api
Platform: UNKNOWN
Classifier: Programming Language :: Python :: 3
Classifier: Operating System :: OS Independent
Requires-Python: >=3.7
Requires-Dist: numpy
Requires-Dist: matplotlib
Requires-Dist: tqdm
Requires-Dist: opencv-python
Requires-Dist: h5py
Requires-Dist: overrides
Requires-Dist: transforms3d
Requires-Dist: prefetch-generator
Requires-Dist: returns
Requires-Dist: pims
Requires-Dist: simple-caching
